nonebot/adapters/telegram/__init__.py
nonebot/adapters/telegram/adapter.py
nonebot/adapters/telegram/api.py
nonebot/adapters/telegram/bot.py
nonebot/adapters/telegram/config.py
nonebot/adapters/telegram/event.py
nonebot/adapters/telegram/exception.py
nonebot/adapters/telegram/message.py
nonebot/adapters/telegram/model.py
nonebot/adapters/telegram/permission.py
nonebot/adapters/telegram/utils.py
nonebot_adapter_telegram-0.1.0b20.dist-info/WHEEL
nonebot_adapter_telegram-0.1.0b20.dist-info/METADATA
nonebot_adapter_telegram-0.1.0b20.dist-info/licenses/LICENSE
nonebot_adapter_telegram-0.1.0b20.dist-info/RECORD
