Metadata-Version: 2.1
Name: nonebot-adapter-telegram
Version: 0.1.0b20
Summary: Telegram Adapter for NoneBot2
License: MIT
Keywords: bot,telegram
Author-email: Jigsaw <j1g5aw@foxmail.com>
Requires-Python: >=3.9,<4.0
Classifier: Development Status :: 5 - Production/Stable
Classifier: Framework :: Robot Framework
Classifier: Framework :: Robot Framework :: Library
Classifier: License :: OSI Approved :: MIT License
Classifier: Operating System :: OS Independent
Classifier: Programming Language :: Python :: 3
Project-URL: changelog, https://github.com/nonebot/adapter-telegram/blob/beta/CHANGELOG.md
Project-URL: documentation, https://github.com/nonebot/adapter-telegram/blob/beta/MANUAL.md
Project-URL: homepage, https://nonebot.dev/
Project-URL: repository, https://github.com/nonebot/adapter-telegram
